cnxman
