Metadata-Version: 1.2
Name: cnxman
Version: 0.0.2
Summary: A pretty simple framework for managin connections to things.
Home-page: http://cnxman.readthedocs.io/en/latest/index.html
Author: Pat Daburu
Author-email: pat@daburu.net
License: MIT
Download-URL: https://github.com/pblair/cnxman/archive/0.0.2.tar.gz
Keywords: plugin
Platform: UNKNOWN
Classifier: Development Status :: 3 - Alpha
Classifier: Intended Audience :: Developers
Classifier: Topic :: Software Development :: Libraries
Classifier: License :: OSI Approved :: MIT License
Classifier: Programming Language :: Python :: 3.6
Requires-Python: >=3.6.1
